README.md
setup.py
queick/__init__.py
queick/cli.py
queick/constants.py
queick/exceptions.py
queick/job.py
queick/job_queue.py
queick/job_receiver.py
queick/logger.py
queick/network_watcher.py
queick/queue_manager.py
queick/scheduler.py
queick/scheduling_time.py
queick/worker.py
queick.egg-info/PKG-INFO
queick.egg-info/SOURCES.txt
queick.egg-info/dependency_links.txt
queick.egg-info/entry_points.txt
queick.egg-info/top_level.txt
tests/__init__.py
tests/test_job.py
tests/test_queue_manager.py
tests/testfunc.py