Metadata-Version: 2.1
Name: queick
Version: 1.2.0
Summary: A lightweight job-queue management system
Home-page: https://github.com/asmsuechan/queick
Author: asmsuechan
Author-email: suenagaryoutaabc@gmail.com
License: UNKNOWN
Platform: UNKNOWN
